ghostdebug/__init__.py
ghostdebug/debug.py
ghostdebug-0.1.0.dist-info/licenses/LICENSE
ghostdebug-0.1.0.dist-info/METADATA
ghostdebug-0.1.0.dist-info/WHEEL
ghostdebug-0.1.0.dist-info/top_level.txt
ghostdebug-0.1.0.dist-info/RECORD
