Metadata-Version: 2.4
Name: ghostdebug
Version: 0.1.0
Summary: A simple backend debugger for python inspired by Unity's Debug system
Author: Nnaa4y
License: MIT
Classifier: Programming Language :: Python :: 3
Classifier: License :: OSI Approved :: MIT License
Classifier: Operating System :: OS Independent
Requires-Python: >=3.10
License-File: LICENSE
Dynamic: license-file
